airflow_dag_artifact/__init__.py
airflow_dag_artifact/_version.py
airflow_dag_artifact/api.py
airflow_dag_artifact/aws_mwaa.py
airflow_dag_artifact/model.py
airflow_dag_artifact/paths.py
airflow_dag_artifact/docs/__init__.py
airflow_dag_artifact/tests/__init__.py
airflow_dag_artifact/tests/helper.py
airflow_dag_artifact/tests/mock_aws.py
airflow_dag_artifact/vendor/__init__.py
airflow_dag_artifact/vendor/hashes.py
airflow_dag_artifact/vendor/pytest_cov_helper.py
airflow_dag_artifact-0.2.1.dist-info/AUTHORS.rst
airflow_dag_artifact-0.2.1.dist-info/LICENSE.txt
airflow_dag_artifact-0.2.1.dist-info/METADATA
airflow_dag_artifact-0.2.1.dist-info/WHEEL
airflow_dag_artifact-0.2.1.dist-info/top_level.txt
airflow_dag_artifact-0.2.1.dist-info/RECORD
