Metadata-Version: 2.1
Name: airflow-dag-artifact
Version: 0.2.1
Summary: Airflow Dag Artifact versioning and alias Management for blue/green, canary deployment, and roll back for production failure.
Home-page: https://github.com/MacHu-GWU/airflow_dag_artifact-project
Download-URL: https://pypi.python.org/pypi/airflow_dag_artifact/0.2.1#downloads
Author: Sanhe Hu
Author-email: husanhe@gmail.com
Maintainer: Sanhe Hu
Maintainer-email: husanhe@gmail.com
License: MIT
Platform: Windows
Platform: MacOS
Platform: Unix
Classifier: Development Status :: 4 - Beta
Classifier: Intended Audience :: Developers
Classifier: License :: OSI Approved :: MIT License
Classifier: Natural Language :: English
Classifier: Operating System :: Microsoft :: Windows
Classifier: Operating System :: MacOS
Classifier: Operating System :: Unix
Classifier: Programming Language :: Python
Classifier: Programming Language :: Python :: 3.7
Classifier: Programming Language :: Python :: 3.8
Classifier: Programming Language :: Python :: 3.9
Classifier: Programming Language :: Python :: 3.10
Classifier: Programming Language :: Python :: 3 :: Only
License-File: LICENSE.txt
License-File: AUTHORS.rst
Requires-Dist: boto3
Requires-Dist: s3pathlib (<3.0.0,>=2.0.1)
Requires-Dist: versioned (<1.0.0,>=0.4.2)
Provides-Extra: docs
Requires-Dist: sphinx (==5.3.0) ; extra == 'docs'
Requires-Dist: sphinx-jinja (==2.0.2) ; extra == 'docs'
Requires-Dist: sphinx-copybutton (==0.5.1) ; extra == 'docs'
Requires-Dist: rstobj (==1.2.1) ; extra == 'docs'
Requires-Dist: docfly (==1.1.1) ; extra == 'docs'
Requires-Dist: furo (==2023.03.27) ; extra == 'docs'
Provides-Extra: tests
Requires-Dist: pytest ; extra == 'tests'
Requires-Dist: pytest-cov ; extra == 'tests'
Requires-Dist: moto ; extra == 'tests'
Requires-Dist: rich ; extra == 'tests'
